mypackage/Scrap_and_predict_accounts.py
mypackage/__init__.py
mypackage/classfication.py
mypackage/config.py
mypackage/data_processing.py
mypackage/facebook_scraping.py
mypackage/useful_function.py
mypackage/pages/Train_Model.py
mypackage/pages/__init__.py
tests/__init__.py
tests/classfication.py
tests/test_classfication.py
package_facebook_scrapper-0.1.dist-info/LICENSE.txt
package_facebook_scrapper-0.1.dist-info/METADATA
package_facebook_scrapper-0.1.dist-info/WHEEL
package_facebook_scrapper-0.1.dist-info/top_level.txt
package_facebook_scrapper-0.1.dist-info/RECORD
